.pylintrc
CONTRIBUTING.md
LICENSE
MANIFEST.in
NEWS
README.md
meson.build
meson_options.txt
pyproject.toml
LICENSES/0BSD.txt
LICENSES/ISC.txt
src/sphinxygen/__init__.py
src/sphinxygen/sphinxygen.py
src/sphinxygen.egg-info/PKG-INFO
src/sphinxygen.egg-info/SOURCES.txt
src/sphinxygen.egg-info/dependency_links.txt
src/sphinxygen.egg-info/entry_points.txt
src/sphinxygen.egg-info/requires.txt
src/sphinxygen.egg-info/top_level.txt
test/test_sphinxygen.py